{
  "apiPort": 8080,
  "webPort": 3000,
  "bind": "127.0.0.1",
  "host": "http://localhost:8080",
  "api": "http://localhost:8080",
  "mongo": "mongodb://localhost:27017/pronoundb",
  "secret": "aaaaaaaaaaaaaaaaaaaaaaaaaaaaaaaaaaaaaaaaaaaaaaaaa",
  "oauth": {
    "discord": [ "client id", "client secret" ],
    "github": [ "client id", "client secret", "token" ],
    "twitch": [ "client id", "client secret" ],
    "twitter": [ "client id", "client secret" ],
    "facebook": [ "client id", "client secret" ],
    "microsoft": [ "client id", "client secret" ]
  }
}
